encrypted_files/__init__.py
encrypted_files/apps.py
encrypted_files/fields.py
encrypted_files/storage.py
encrypted_files/views.py
encrypted_files/migrations/__init__.py
encrypted_files/tests/__init__.py
encrypted_files/tests/test_encrypted_fields.py
encrypted_files/tests/test_models/__init__.py
encrypted_files/tests/test_models/apps.py
encrypted_files/tests/test_models/models.py
django_filefield_encrypted-0.1.1.dist-info/LICENSE
django_filefield_encrypted-0.1.1.dist-info/METADATA
django_filefield_encrypted-0.1.1.dist-info/WHEEL
django_filefield_encrypted-0.1.1.dist-info/top_level.txt
django_filefield_encrypted-0.1.1.dist-info/RECORD
