Metadata-Version: 2.1
Name: django-filefield-encrypted
Version: 0.1.1
Summary: Encryted file field for Django
Home-page: https://github.com/gsteixeira/django-filefield-encrypted
Author: Gustavo Selbach Teixeira
Author-email: gsteixei@gmail.com
License: GNU License
Classifier: Development Status :: 5 - Production/Stable
Classifier: Topic :: Utilities
License-File: LICENSE
